{
    "/location/location/contains": "/स्थान/स्थान/शामिल_है",
    "/people/person/nationality": "/लोग/व्यक्ति/राष्ट्रीयता",
    "/people/person/place_lived": "/लोग/व्यक्ति/रहने_का_स्थान",
    "/business/person/company": "/व्यापार/व्यक्ति/कंपनी",
    "/location/country/capital": "/स्थान/देश/राजधानी",
    "/location/neighborhood/neighborhood_of": "/स्थान/पड़ोस/का_पड़ोस",
    "/people/person/place_of_birth": "/लोग/व्यक्ति/जन्म_स्थान",
    "/location/country/administrative_divisions": "/स्थान/देश/प्रशासनिक_विभाजन",
    "/location/administrative_division/country": "/स्थान/प्रशासनिक_विभाजन/देश",
    "/people/deceased_person/place_of_death": "/लोग/मृत_व्यक्ति/मृत्यु_का_स्थान",
    "/people/person/children": "/लोग/व्यक्ति/बच्चे",
    "/business/company/founders": "/व्यापार/कंपनी/संस्थापक",
    "/business/company/place_founded": "/व्यापार/कंपनी/स्थापना_का_स्थान",
    "/business/company_shareholder/major_shareholder_of": "/व्यापार/कंपनी_शेयरधारक/का_प्रमुख_शेयरधारक",
    "/sports/sports_team_location/teams": "/खेल/खेल_टीम_स्थान/टीमें",
    "/sports/sports_team/location": "/खेल/खेल_टीम/स्थान",
    "/business/company/major_shareholders": "/व्यापार/कंपनी/प्रमुख_शेयरधारक",
    "/people/person/religion": "/लोग/व्यक्ति/धर्म",
    "/business/company/advisors": "/व्यापार/कंपनी/सलाहकार",
    "/people/ethnicity/geographic_distribution": "/लोग/जातीयता/भौगोलिक_वितरण",
    "/people/person/ethnicity": "/लोग/व्यक्ति/जातीयता",
    "/people/ethnicity/people": "/लोग/जातीयता/लोग",
    "/people/person/profession": "/लोग/व्यक्ति/पेशा",
    "/business/company/industry": "/व्यापार/कंपनी/उद्योग"
}